Metadata-Version: 2.1
Name: uniffi-zcash
Version: 0.0.0
Summary: Zcash librustzcash python FFI layer
Author: zcash
Classifier: Intended Audience :: Developers
Classifier: Topic :: Software Development :: Libraries
Classifier: Programming Language :: Python
Classifier: Programming Language :: C
License-File: LICENSE.txt
